arkitect-0.2.10.dist-info/METADATA
arkitect-0.2.10.dist-info/WHEEL
arkitect-0.2.10.dist-info/entry_points.txt
arkitect/LICENSE
arkitect/README.md
arkitect/README_en.md
arkitect/__init__.py
arkitect/core/__init__.py
arkitect/core/client/__init__.py
arkitect/core/client/base.py
arkitect/core/client/http.py
arkitect/core/client/redis.py
arkitect/core/client/sse.py
arkitect/core/component/__init__.py
arkitect/core/component/agent/__init__.py
arkitect/core/component/agent/base_agent.py
arkitect/core/component/agent/default_agent.py
arkitect/core/component/agent/parallel_agent.py
arkitect/core/component/asr/__init__.py
arkitect/core/component/asr/asr_client.py
arkitect/core/component/asr/constants.py
arkitect/core/component/asr/model.py
arkitect/core/component/bot/__init__.py
arkitect/core/component/bot/middleware.py
arkitect/core/component/bot/server.py
arkitect/core/component/checkpoint/__init__.py
arkitect/core/component/checkpoint/base_checkpoint_service.py
arkitect/core/component/checkpoint/checkpoint.py
arkitect/core/component/checkpoint/in_memory_checkpoint_service.py
arkitect/core/component/checkpoint/redis_checkpoint_service.py
arkitect/core/component/context/__init__.py
arkitect/core/component/context/chat_completion.py
arkitect/core/component/context/context.py
arkitect/core/component/context/context_completion.py
arkitect/core/component/context/hooks.py
arkitect/core/component/context/model.py
arkitect/core/component/context/utils.py
arkitect/core/component/llm/__init__.py
arkitect/core/component/llm/base.py
arkitect/core/component/llm/function_call.py
arkitect/core/component/llm/llm.py
arkitect/core/component/llm/utils.py
arkitect/core/component/llm_event_stream/__init__.py
arkitect/core/component/llm_event_stream/chat_completion.py
arkitect/core/component/llm_event_stream/hooks.py
arkitect/core/component/llm_event_stream/llm_event_stream.py
arkitect/core/component/llm_event_stream/model.py
arkitect/core/component/llm_event_stream/utils.py
arkitect/core/component/output_parser/__init__.py
arkitect/core/component/output_parser/rag_output.py
arkitect-0.2.10.dist-info/RECORD
