Metadata-Version: 2.1
Name: arkitect
Version: 0.2.10
Author-Email: "wangsen.0914" <wangsen.0914@bytedance.com>
Requires-Python: <4.0,>=3.10
Requires-Dist: langchain-core>=0.3.35
Requires-Dist: langchain>=0.1.0
Requires-Dist: fastapi<1.0.0,>=0.100.0
Requires-Dist: uvicorn<0.30.0,>=0.22.0
Requires-Dist: opentelemetry-api<2.0.0,>=1.22.0
Requires-Dist: pydantic<3.0.0,>=2.0.0
Requires-Dist: opentelemetry-exporter-otlp<2.0.0,>=1.22.0
Requires-Dist: jinja2<4.0.0,>=3.1.2
Requires-Dist: structlog<25.0.0,>=23.1.0
Requires-Dist: opentelemetry-sdk<2.0.0,>=1.22.0
Requires-Dist: volcengine-python-sdk>=3.0.10
Requires-Dist: httpx>=0.27.0
Requires-Dist: pytz>=2020.5
Requires-Dist: tenacity==8.3.0
Requires-Dist: uvloop>=0.19.0; sys_platform != "win32"
Requires-Dist: orjson<3.10.7
Requires-Dist: aiofiles==23.2.1
Requires-Dist: tos<3.0.0,>=2.8.1
Requires-Dist: mcp>=1.8.1
Requires-Dist: aiohttp>=3.11.13
Requires-Dist: websockets>=14.0
Requires-Dist: redis>=6.1.0
